smartagents/__init__.py
smartagents-0.0.1.dist-info/LICENSE
smartagents-0.0.1.dist-info/METADATA
smartagents-0.0.1.dist-info/WHEEL
smartagents-0.0.1.dist-info/top_level.txt
smartagents-0.0.1.dist-info/RECORD
