Metadata-Version: 2.2
Name: smartagents
Version: 0.0.1
Summary: smartagents
Author: abhishek
Project-URL: Homepage, https://github.com/abhishekkrthakur/smartagents
Project-URL: Issues, https://github.com/abhishekkrthakur/smartagents/issues
Keywords: smartagents
Classifier: Development Status :: 5 - Production/Stable
Classifier: License :: OSI Approved :: Apache Software License
Classifier: Operating System :: OS Independent
Classifier: Programming Language :: Python :: 3.10
Classifier: Programming Language :: Python :: 3.11
Classifier: Topic :: Scientific/Engineering :: Artificial Intelligence
License-File: LICENSE
